{
  "contact_id": "e357cd2a-f57d-4332-9e85-0e961622260a",
  "name": "Niyoine Thompson",
  "email": "lanaewilks072@gmail.com",
  "phone": "+18392991283",
  "market": "georgia",
  "va_date": "2026-04-16",
  "rec": "APPROVE",
  "confidence": "HIGH",
  "ai_summary": "Niyoine Thompson is a 21-year-old caregiver with daycare and CNA experience, seeking part-time work in the Augusta area with open availability. She handles conflicts by separating children and speaking with them privately, and would be a great fit due to her fun personality and genuine love for children."
}